commit2jira/__init__.py
commit2jira/cli.py
commit2jira/install.py
commit2jira-0.1.7.dist-info/METADATA
commit2jira-0.1.7.dist-info/WHEEL
commit2jira-0.1.7.dist-info/entry_points.txt
commit2jira-0.1.7.dist-info/top_level.txt
commit2jira-0.1.7.dist-info/RECORD
